rumor_tools/__init__.py
rumor_tools/classifier.py
rumor_tools/preprocess.py
rumor_tools/quantifier.py
rumor_tools-0.0.2.dev1.dist-info/DESCRIPTION.rst
rumor_tools-0.0.2.dev1.dist-info/METADATA
rumor_tools-0.0.2.dev1.dist-info/RECORD
rumor_tools-0.0.2.dev1.dist-info/WHEEL
rumor_tools-0.0.2.dev1.dist-info/metadata.json
rumor_tools-0.0.2.dev1.dist-info/top_level.txt
